<?xml version="1.0"?>
<!--
/**
 * BS_Meda extension
 * 
 * @category       BS
 * @package        BS_Meda
 * @copyright      Copyright (c) 2018
 */
-->
<config>
    <acl>
        <resources>
            <admin>
                <children>
                    <system>
                        <children>
                            <config>
                                <children>
                                    <bs_meda translate="title" module="bs_meda">
                                        <title>Meda</title>
                                    </bs_meda>
                                </children>
                            </config>
                        </children>
                    </system>
                    <bs_work>
                        <children>
                            <meda translate="title" module="bs_meda">
                                <title>MEDA</title>
                                <sort_order>100</sort_order>
                                <children>
                                    <new translate="title"><title>New</title></new>
                                    <edit translate="title"><title>Edit</title></edit>
                                    <delete translate="title"><title>Delete</title></delete>
                                </children>
                            </meda>
                        </children>
                    </bs_work>

                </children>
            </admin>
        </resources>
    </acl>
    <menu>
        <bs_work>
            <children>
                <meda translate="title" module="bs_meda">
                    <title>MEDA</title>
                    <action>adminhtml/meda_meda</action>
                    <sort_order>100</sort_order>
                </meda>
            </children>
        </bs_work>

    </menu>
</config>
